LICENSE.txt
MANIFEST.in
README.md
setup.cfg
setup.py
.eggs/README.txt
.eggs/Pygments-2.13.0-py3.10.egg/EGG-INFO/entry_points.txt
.eggs/Pygments-2.13.0-py3.10.egg/EGG-INFO/requires.txt
.eggs/Pygments-2.13.0-py3.10.egg/EGG-INFO/top_level.txt
payok/__init__.py
payok/payok_api.py
payok.egg-info/PKG-INFO
payok.egg-info/SOURCES.txt
payok.egg-info/dependency_links.txt
payok.egg-info/not-zip-safe
payok.egg-info/requires.txt
payok.egg-info/top_level.txt