Metadata-Version: 2.1
Name: payok
Version: 1.2
Summary: Python payok.io API Client
Home-page: https://github.com/re-oos/payok
Author: except
Author-email: 994b3d@gmail.com
License: MIT LICENSE
Platform: UNKNOWN
License-File: LICENSE.txt
